vastai_client/__init__.py
vastai_client/models.py
vastai_client/vast_client.py
vastai_client/vast_utils.py
vastai_client-0.1.1.dist-info/LICENSE
vastai_client-0.1.1.dist-info/METADATA
vastai_client-0.1.1.dist-info/WHEEL
vastai_client-0.1.1.dist-info/RECORD
