Metadata-Version: 2.1
Name: vastai-client
Version: 0.1.1
Summary: Python client for the Vast.ai cloud rent service.
Home-page: https://github.com/Barahlush/vastai-client
License: MIT
Author: Georgiy Kozhevnikov
Requires-Python: >=3.7,<4.0
Classifier: Development Status :: 3 - Alpha
Classifier: Intended Audience :: Developers
Classifier: License :: OSI Approved :: MIT License
Classifier: Operating System :: OS Independent
Classifier: Programming Language :: Python :: 3
Classifier: Programming Language :: Python :: 3.7
Classifier: Programming Language :: Python :: 3.8
Classifier: Programming Language :: Python :: 3.9
Classifier: Programming Language :: Python :: 3.10
Classifier: Programming Language :: Python :: 3.11
Classifier: Topic :: Software Development :: Libraries :: Python Modules
Requires-Dist: dacite (>=1.7.0,<2.0.0)
Requires-Dist: loguru (>=0.6.0,<0.7.0)
Project-URL: Repository, https://github.com/Barahlush/vastai-client
